qterm/__init__.py
qterm/qterm.py
qterm/templates/__init__.py
qterm/templates/templates.py
qterm-0.0.2.dist-info/LICENSE
qterm-0.0.2.dist-info/METADATA
qterm-0.0.2.dist-info/WHEEL
qterm-0.0.2.dist-info/top_level.txt
qterm-0.0.2.dist-info/RECORD
