Metadata-Version: 2.1
Name: qterm
Version: 0.0.2
Summary: QTerm is a Python module for spawning child applications and controlling them automatically
Home-page: https://github.com/SH659/QTerm
Author: SH21
Author-email: anosovigor404@gmail.com
License: UNKNOWN
Platform: UNKNOWN
Classifier: Programming Language :: Python :: 3
Classifier: License :: OSI Approved :: GNU Affero General Public License v3
Classifier: Operating System :: Microsoft :: Windows
Requires-Python: >=3.6
License-File: LICENSE
Requires-Dist: wexpect (==4.0.0)
